reedjobs/__init__.py
reedjobs/_model.py
reedjobs/_types.py
reedjobs/client.py
reedjobs/utils.py
reedjobs-0.1.1.dist-info/LICENSE
reedjobs-0.1.1.dist-info/METADATA
reedjobs-0.1.1.dist-info/WHEEL
reedjobs-0.1.1.dist-info/top_level.txt
reedjobs-0.1.1.dist-info/RECORD
