Metadata-Version: 2.1
Name: reedjobs
Version: 0.1.1
Summary: A Python client for the Reed Jobseeker API.
Home-page: https://github.com/LukeBilsborrow/reed-api-client
Author: LukeBilsborrow
Classifier: Programming Language :: Python :: 3
Classifier: License :: OSI Approved :: MIT License
Classifier: Operating System :: OS Independent
Requires-Python: >=3.8
License-File: LICENSE
Requires-Dist: httpx >=0.27.2
Requires-Dist: pydantic >=2.9.2
